{"title":"VSCode插件大全","uid":"5632221ad69588971354770029883ced","slug":"5632221ad69588971354770029883ced","date":"2020-04-25T17:55:05.000Z","updated":"2023-08-22T04:44:05.507Z","comments":true,"path":"api/articles/5632221ad69588971354770029883ced.json","keywords":null,"cover":"https://source.unsplash.com/wh-RPfR_3_M/1600x900","content":"<p>上一篇文章<a href=\"https://blog.csdn.net/tridiamond6/article/details/105455341\">《VSCode 常用快捷键大全》</a>，我们了解到了 VSCode 中的常用快捷键。学会了快捷键可以让我们更高效和迅速的编写代码。但是没有 IDE 中的一些辅助功能，还是美中不足。</p>\n<p>VSCode 没有安装插件，就等同于一把枪没有安装配件，打把的时候还是缺失精准度，开枪的时候也会有很重的后坐力。当然没有插件，也可以很好的编写代码，就是没有那么强而已。</p>\n<p>所以这篇文章会给大家介绍 VSCode 中最常用的插件，让我们的编辑器加上一双翅膀，让我们在编写代码的过程中如虎添翼的感觉。</p>\n<blockquote><span class=\"custom-blockquote-svg\"><svg width=\"24\" height=\"24\" viewBox=\"0 0 24 24\" fill=\"\" xmlns=\"http://www.w3.org/2000/svg\" data-reactroot=\"\">\n<path fill=\"\" d=\"M22 12C22 6.5 17.5 2 12 2C6.5 2 2 6.5 2 12C2 17.5 6.5 22 12 22C13.8 22 15.5 21.5 17 20.6L22 22L20.7 17C21.5 15.5 22 13.8 22 12Z\" undefined=\"1\"></path>\n<path fill=\"\" d=\"M15.97 11.5H16.04C17.12 11.5 18 12.38 18 13.47V13.53C18 14.62 17.12 15.5 16.03 15.5H15.96C14.88 15.5 14 14.62 14 13.53V13.46C14 12.38 14.88 11.5 15.97 11.5Z\" undefined=\"1\"></path>\n<path fill=\"\" d=\"M7.97 11.5H8.04C9.12 11.5 10 12.38 10 13.47V13.53C10 14.62 9.12 15.5 8.03 15.5H7.97C6.88 15.5 6 14.62 6 13.53V13.46C6 12.38 6.88 11.5 7.97 11.5Z\" undefined=\"1\"></path>\n<path stroke-linejoin=\"round\" stroke-linecap=\"round\" stroke-miterlimit=\"10\" stroke-width=\"2\" stroke=\"\" d=\"M17 8.5C15.23 8.97 14.07 10.84 14.01 13.27C14 13.33 14 13.4 14 13.47V13.5\"></path>\n<path stroke-linejoin=\"round\" stroke-linecap=\"round\" stroke-miterlimit=\"10\" stroke-width=\"2\" stroke=\"\" d=\"M9 8.5C7.23 8.97 6.07 10.84 6.01 13.27C6 13.33 6 13.4 6 13.47V13.5\"></path>\n<path stroke-linejoin=\"round\" stroke-linecap=\"round\" stroke-miterlimit=\"10\" stroke-width=\"2\" stroke=\"\" d=\"M15.97 11.5H16.04C17.12 11.5 18 12.38 18 13.47V13.53C18 14.62 17.12 15.5 16.03 15.5H15.96C14.88 15.5 14 14.62 14 13.53V13.46C14 12.38 14.88 11.5 15.97 11.5Z\"></path>\n<path stroke-linejoin=\"round\" stroke-linecap=\"round\" stroke-miterlimit=\"10\" stroke-width=\"2\" stroke=\"\" d=\"M7.97 11.5H8.04C9.12 11.5 10 12.38 10 13.47V13.53C10 14.62 9.12 15.5 8.03 15.5H7.97C6.88 15.5 6 14.62 6 13.53V13.46C6 12.38 6.88 11.5 7.97 11.5Z\"></path>\n</svg>\n</span><p>🌟 所有插件，只要搜索插件名就能找到哦！</p></blockquote>\n<p><img src=\"https://imgconvert.csdnimg.cn/aHR0cHM6Ly91c2VyLWdvbGQtY2RuLnhpdHUuaW8vMjAyMC80LzExLzE3MTY4NzdiNmRhMzMzNGM?x-oss-process=image/format,png\"></p>\n<h1 id=\"「一」国人必备集合\"><a href=\"#「一」国人必备集合\" class=\"headerlink\" title=\"「一」国人必备集合\"></a>「一」国人必备集合</h1><p>这些插件都是我们作为中国人必备的，妈妈再也不怕我们看不懂英文了。</p>\n<p><img src=\"https://imgconvert.csdnimg.cn/aHR0cHM6Ly91c2VyLWdvbGQtY2RuLnhpdHUuaW8vMjAyMC80LzEyLzE3MTZkMWNjMDhjNTA1NDM?x-oss-process=image/format,png\"></p>\n<h2 id=\"VSCode-中文简体包\"><a href=\"#VSCode-中文简体包\" class=\"headerlink\" title=\"VSCode 中文简体包\"></a>VSCode 中文简体包</h2><p><code>插件名：Chinese (Simplified) Language Pack for Visual Studio Code</code></p>\n<p>这个插件一键把整个 VSCode 的文字转换成中文。一个全中文化的 IDE 是我们特别需要的。而且这个是官方汉化包，理解无障碍。</p>\n<p><img src=\"https://img-blog.csdnimg.cn/20200417232726769.png?x-oss-process=image/watermark,type_ZmFuZ3poZW5naGVpdGk,shadow_10,text_aHR0cHM6Ly9ibG9nLmNzZG4ubmV0L1RyaURpYW1vbmQ2,size_16,color_FFFFFF,t_70\"></p>\n<p><img src=\"https://imgconvert.csdnimg.cn/aHR0cHM6Ly91c2VyLWdvbGQtY2RuLnhpdHUuaW8vMjAyMC80LzEyLzE3MTZkMWNjMDhjNTA1NDM?x-oss-process=image/format,png\"></p>\n<h2 id=\"代码翻译\"><a href=\"#代码翻译\" class=\"headerlink\" title=\"代码翻译\"></a>代码翻译</h2><p><code>插件名：翻译(英汉词典)</code></p>\n<p>英语不是很好的童鞋，在写代码的时候经常会使用“某道翻译”，但是其实对于代码来说，很多时候我们会用<code>驼峰</code>、<code>小驼峰</code>、<code>下划线</code>等等写法来写变量名、属性名、类名和方法名的。这种写法想使用“某道翻译”在编辑器中悬浮翻译就是不可能了。</p>\n<p>找了很久我为大家找到一个非常好用的一个插件可以解决这个问题！</p>\n<blockquote><span class=\"custom-blockquote-svg\"><svg width=\"24\" height=\"24\" viewBox=\"0 0 24 24\" fill=\"\" xmlns=\"http://www.w3.org/2000/svg\" data-reactroot=\"\">\n<path fill=\"\" d=\"M22 12C22 6.5 17.5 2 12 2C6.5 2 2 6.5 2 12C2 17.5 6.5 22 12 22C13.8 22 15.5 21.5 17 20.6L22 22L20.7 17C21.5 15.5 22 13.8 22 12Z\" undefined=\"1\"></path>\n<path fill=\"\" d=\"M15.97 11.5H16.04C17.12 11.5 18 12.38 18 13.47V13.53C18 14.62 17.12 15.5 16.03 15.5H15.96C14.88 15.5 14 14.62 14 13.53V13.46C14 12.38 14.88 11.5 15.97 11.5Z\" undefined=\"1\"></path>\n<path fill=\"\" d=\"M7.97 11.5H8.04C9.12 11.5 10 12.38 10 13.47V13.53C10 14.62 9.12 15.5 8.03 15.5H7.97C6.88 15.5 6 14.62 6 13.53V13.46C6 12.38 6.88 11.5 7.97 11.5Z\" undefined=\"1\"></path>\n<path stroke-linejoin=\"round\" stroke-linecap=\"round\" stroke-miterlimit=\"10\" stroke-width=\"2\" stroke=\"\" d=\"M17 8.5C15.23 8.97 14.07 10.84 14.01 13.27C14 13.33 14 13.4 14 13.47V13.5\"></path>\n<path stroke-linejoin=\"round\" stroke-linecap=\"round\" stroke-miterlimit=\"10\" stroke-width=\"2\" stroke=\"\" d=\"M9 8.5C7.23 8.97 6.07 10.84 6.01 13.27C6 13.33 6 13.4 6 13.47V13.5\"></path>\n<path stroke-linejoin=\"round\" stroke-linecap=\"round\" stroke-miterlimit=\"10\" stroke-width=\"2\" stroke=\"\" d=\"M15.97 11.5H16.04C17.12 11.5 18 12.38 18 13.47V13.53C18 14.62 17.12 15.5 16.03 15.5H15.96C14.88 15.5 14 14.62 14 13.53V13.46C14 12.38 14.88 11.5 15.97 11.5Z\"></path>\n<path stroke-linejoin=\"round\" stroke-linecap=\"round\" stroke-miterlimit=\"10\" stroke-width=\"2\" stroke=\"\" d=\"M7.97 11.5H8.04C9.12 11.5 10 12.38 10 13.47V13.53C10 14.62 9.12 15.5 8.03 15.5H7.97C6.88 15.5 6 14.62 6 13.53V13.46C6 12.38 6.88 11.5 7.97 11.5Z\"></path>\n</svg>\n</span><p>本地 77 万词条英汉词典，不依赖任何在线翻译 API，无查询次数限制。可翻译驼峰和下划线命名，及对整个文件中的标识符批量翻译。</p></blockquote>\n<p><img src=\"https://img-blog.csdnimg.cn/20200417233026920.png?x-oss-process=image/watermark,type_ZmFuZ3poZW5naGVpdGk,shadow_10,text_aHR0cHM6Ly9ibG9nLmNzZG4ubmV0L1RyaURpYW1vbmQ2,size_16,color_FFFFFF,t_70\"></p>\n<p><img src=\"https://imgconvert.csdnimg.cn/aHR0cHM6Ly91c2VyLWdvbGQtY2RuLnhpdHUuaW8vMjAyMC80LzEyLzE3MTZkMWNjMDhjNTA1NDM?x-oss-process=image/format,png\"></p>\n<h2 id=\"检测代码英文单词错误\"><a href=\"#检测代码英文单词错误\" class=\"headerlink\" title=\"检测代码英文单词错误\"></a>检测代码英文单词错误</h2><p><code>插件名：Code Spell Checker</code></p>\n<p>一个基本的拼写检查器，可以检测驼峰写法。这个拼写检查程序的目标是帮助捕获常见的拼写错误。在编写代码的时候，我们都是用英文单词，很多时候我们都会写错单词的可能性。用错了单词其实对于维护性是有一定的影响的。</p>\n<p>使用有意义的单词做为方法名、类名和变量名会给自己代码更多的意义和含义。当自己或者别人去查看代码时更容易懂其中的用意。但是如果我们拼错了单词，有些时候就无法理解这个单词是什么意思了。</p>\n<p>所以这个插件对我们来说非常实用，就算是老外都非常多人在使用它。（目前有 100 多万下载量）</p>\n<p><img src=\"https://img-blog.csdnimg.cn/20200418015011197.png?x-oss-process=image/watermark,type_ZmFuZ3poZW5naGVpdGk,shadow_10,text_aHR0cHM6Ly9ibG9nLmNzZG4ubmV0L1RyaURpYW1vbmQ2,size_16,color_FFFFFF,t_70\"></p>\n<p><img src=\"https://imgconvert.csdnimg.cn/aHR0cHM6Ly91c2VyLWdvbGQtY2RuLnhpdHUuaW8vMjAyMC80LzExLzE3MTY4NzdiNmRhMzMzNGM?x-oss-process=image/format,png\"></p>\n<h1 id=\"「二」主题集合\"><a href=\"#「二」主题集合\" class=\"headerlink\" title=\"「二」主题集合\"></a>「二」主题集合</h1><p>一个程序员一天 8-12 个小时都是看着编辑器和代码。如果我们的编辑器不好看，没有一定的美观和吸引力，怎么可能耐看不厌呢？加上长期看代码，一个舒服的主题自然是必备之一。</p>\n<p>这里介绍几款我最喜欢的主题给大家使用。有更多大家喜欢的主题欢迎在评论中提出，我会补充到这里哦！</p>\n<p><img src=\"https://imgconvert.csdnimg.cn/aHR0cHM6Ly91c2VyLWdvbGQtY2RuLnhpdHUuaW8vMjAyMC80LzEyLzE3MTZkMWNjMDhjNTA1NDM?x-oss-process=image/format,png\"></p>\n<h2 id=\"Dracula-Theme\"><a href=\"#Dracula-Theme\" class=\"headerlink\" title=\"Dracula Theme\"></a>Dracula Theme</h2><p><code>主题名：Dracula Official</code></p>\n<p>这款主题主调色是偏深紫色，我用了这个主题至少也有 2-3 年，一直都很喜欢。里面代码的高亮和颜色都很细致，很适合长期看。这个主题的颜色有根据不同的语言做了适配，无论我们是在开发什么语言都非常好看。</p>\n<p><img src=\"https://img-blog.csdnimg.cn/20200417235323559.png?x-oss-process=image/watermark,type_ZmFuZ3poZW5naGVpdGk,shadow_10,text_aHR0cHM6Ly9ibG9nLmNzZG4ubmV0L1RyaURpYW1vbmQ2,size_16,color_FFFFFF,t_70\"><br><img src=\"https://imgconvert.csdnimg.cn/aHR0cHM6Ly91c2VyLWdvbGQtY2RuLnhpdHUuaW8vMjAyMC80LzEyLzE3MTZkMWNjMDhjNTA1NDM?x-oss-process=image/format,png\"></p>\n<h2 id=\"Material-Theme\"><a href=\"#Material-Theme\" class=\"headerlink\" title=\"Material Theme\"></a>Material Theme</h2><p><code>主题名：Material Theme</code></p>\n<p>这款也是非常出名的主题，在非常多的 IDE&#x2F;编辑器都有。用习惯这个主题的可以在 VSCode 中安装使用。使用量也是有 200 多万+。这款主题在我使用<code>SublimeText</code>的时候非常热爱。（也用了好几年）</p>\n<p><img src=\"https://img-blog.csdnimg.cn/202004172349108.png?x-oss-process=image/watermark,type_ZmFuZ3poZW5naGVpdGk,shadow_10,text_aHR0cHM6Ly9ibG9nLmNzZG4ubmV0L1RyaURpYW1vbmQ2,size_16,color_FFFFFF,t_70\"><br><img src=\"https://img-blog.csdnimg.cn/20200417234945684.png?x-oss-process=image/watermark,type_ZmFuZ3poZW5naGVpdGk,shadow_10,text_aHR0cHM6Ly9ibG9nLmNzZG4ubmV0L1RyaURpYW1vbmQ2,size_16,color_FFFFFF,t_70\"></p>\n<p><img src=\"https://imgconvert.csdnimg.cn/aHR0cHM6Ly91c2VyLWdvbGQtY2RuLnhpdHUuaW8vMjAyMC80LzEyLzE3MTZkMWNjMDhjNTA1NDM?x-oss-process=image/format,png\"></p>\n<h2 id=\"Nebula-Theme\"><a href=\"#Nebula-Theme\" class=\"headerlink\" title=\"Nebula Theme\"></a>Nebula Theme</h2><p><code>主题名：Nebula Theme</code></p>\n<p>这一款是我现在在用的小众主题。配色与 Dracula 非常相似，但是有更多的亮色，颜色的变化幅度也没有那么大，相比 Dracula 更为顺眼。当然这个也要看个人喜好哈。</p>\n<p><img src=\"https://img-blog.csdnimg.cn/20200417235607183.png?x-oss-process=image/watermark,type_ZmFuZ3poZW5naGVpdGk,shadow_10,text_aHR0cHM6Ly9ibG9nLmNzZG4ubmV0L1RyaURpYW1vbmQ2,size_16,color_FFFFFF,t_70\"></p>\n<p><img src=\"https://imgconvert.csdnimg.cn/aHR0cHM6Ly91c2VyLWdvbGQtY2RuLnhpdHUuaW8vMjAyMC80LzEyLzE3MTZkMWNjMDhjNTA1NDM?x-oss-process=image/format,png\"></p>\n<h2 id=\"Atom-One-Dark-Theme\"><a href=\"#Atom-One-Dark-Theme\" class=\"headerlink\" title=\"Atom One Dark Theme\"></a>Atom One Dark Theme</h2><p><code>主题名：Atom One Dark Theme</code></p>\n<p>我认识的一些小伙伴用过 Atom，也有这么一部分小伙伴特别喜欢这个主题。</p>\n<p><img src=\"https://img-blog.csdnimg.cn/20200418000044378.png?x-oss-process=image/watermark,type_ZmFuZ3poZW5naGVpdGk,shadow_10,text_aHR0cHM6Ly9ibG9nLmNzZG4ubmV0L1RyaURpYW1vbmQ2,size_16,color_FFFFFF,t_70\"></p>\n<p><img src=\"https://imgconvert.csdnimg.cn/aHR0cHM6Ly91c2VyLWdvbGQtY2RuLnhpdHUuaW8vMjAyMC80LzEyLzE3MTZkMWNjMDhjNTA1NDM?x-oss-process=image/format,png\"></p>\n<h2 id=\"One-Monokai-Theme\"><a href=\"#One-Monokai-Theme\" class=\"headerlink\" title=\"One Monokai Theme\"></a>One Monokai Theme</h2><p><code>主题名：One Monokai Theme</code></p>\n<p>对长期使用<code>SublimeText</code>的<code>Monokai</code>的童鞋们，对这款主题应该感兴趣。毕竟 Monokai 主题陪伴了我们挺长一段时间的。（不好了要暴露年龄了 😂）</p>\n<p><img src=\"https://img-blog.csdnimg.cn/20200418001250130.png?x-oss-process=image/watermark,type_ZmFuZ3poZW5naGVpdGk,shadow_10,text_aHR0cHM6Ly9ibG9nLmNzZG4ubmV0L1RyaURpYW1vbmQ2,size_16,color_FFFFFF,t_70\" alt=\"在这里插入图片描述\"></p>\n<p><img src=\"https://imgconvert.csdnimg.cn/aHR0cHM6Ly91c2VyLWdvbGQtY2RuLnhpdHUuaW8vMjAyMC80LzEyLzE3MTZkMWNjMDhjNTA1NDM?x-oss-process=image/format,png\"></p>\n<h2 id=\"GitHub-Plus-Theme\"><a href=\"#GitHub-Plus-Theme\" class=\"headerlink\" title=\"GitHub Plus Theme\"></a>GitHub Plus Theme</h2><p><code>主题名：GitHub Plus Theme</code></p>\n<p>对终于有一个白色的主题了，但是个人对白色的主题不怎么感冒。最近连微信都加入了黑暗世界，所以我已经习惯所有 UI 都是黑暗模式了。但是毕竟还是有童鞋特别喜爱白色的。</p>\n<p>这里推荐一款与 GitHub 一样色系的白色主题（我可以说是我唯一可以考虑使用白色的一款，有童鞋有自己喜欢的白色主题可以在评论中留言给我哦！）</p>\n<p><img src=\"https://img-blog.csdnimg.cn/20200418000815658.png?x-oss-process=image/watermark,type_ZmFuZ3poZW5naGVpdGk,shadow_10,text_aHR0cHM6Ly9ibG9nLmNzZG4ubmV0L1RyaURpYW1vbmQ2,size_16,color_FFFFFF,t_70\"></p>\n<p><img src=\"https://imgconvert.csdnimg.cn/aHR0cHM6Ly91c2VyLWdvbGQtY2RuLnhpdHUuaW8vMjAyMC80LzEyLzE3MTZkMWNjMDhjNTA1NDM?x-oss-process=image/format,png\"></p>\n<blockquote><span class=\"custom-blockquote-svg\"><svg width=\"24\" height=\"24\" viewBox=\"0 0 24 24\" fill=\"\" xmlns=\"http://www.w3.org/2000/svg\" data-reactroot=\"\">\n<path fill=\"\" d=\"M22 12C22 6.5 17.5 2 12 2C6.5 2 2 6.5 2 12C2 17.5 6.5 22 12 22C13.8 22 15.5 21.5 17 20.6L22 22L20.7 17C21.5 15.5 22 13.8 22 12Z\" undefined=\"1\"></path>\n<path fill=\"\" d=\"M15.97 11.5H16.04C17.12 11.5 18 12.38 18 13.47V13.53C18 14.62 17.12 15.5 16.03 15.5H15.96C14.88 15.5 14 14.62 14 13.53V13.46C14 12.38 14.88 11.5 15.97 11.5Z\" undefined=\"1\"></path>\n<path fill=\"\" d=\"M7.97 11.5H8.04C9.12 11.5 10 12.38 10 13.47V13.53C10 14.62 9.12 15.5 8.03 15.5H7.97C6.88 15.5 6 14.62 6 13.53V13.46C6 12.38 6.88 11.5 7.97 11.5Z\" undefined=\"1\"></path>\n<path stroke-linejoin=\"round\" stroke-linecap=\"round\" stroke-miterlimit=\"10\" stroke-width=\"2\" stroke=\"\" d=\"M17 8.5C15.23 8.97 14.07 10.84 14.01 13.27C14 13.33 14 13.4 14 13.47V13.5\"></path>\n<path stroke-linejoin=\"round\" stroke-linecap=\"round\" stroke-miterlimit=\"10\" stroke-width=\"2\" stroke=\"\" d=\"M9 8.5C7.23 8.97 6.07 10.84 6.01 13.27C6 13.33 6 13.4 6 13.47V13.5\"></path>\n<path stroke-linejoin=\"round\" stroke-linecap=\"round\" stroke-miterlimit=\"10\" stroke-width=\"2\" stroke=\"\" d=\"M15.97 11.5H16.04C17.12 11.5 18 12.38 18 13.47V13.53C18 14.62 17.12 15.5 16.03 15.5H15.96C14.88 15.5 14 14.62 14 13.53V13.46C14 12.38 14.88 11.5 15.97 11.5Z\"></path>\n<path stroke-linejoin=\"round\" stroke-linecap=\"round\" stroke-miterlimit=\"10\" stroke-width=\"2\" stroke=\"\" d=\"M7.97 11.5H8.04C9.12 11.5 10 12.38 10 13.47V13.53C10 14.62 9.12 15.5 8.03 15.5H7.97C6.88 15.5 6 14.62 6 13.53V13.46C6 12.38 6.88 11.5 7.97 11.5Z\"></path>\n</svg>\n</span><p>🌟 小总结<br>VSCode 中还有非常多的主题可以选择，如果我推荐的主题中没有你们喜欢的，可以在插件搜索框中输入<code>theme</code>，就会出来很多的主题供大家自由选择哦！</p></blockquote>\n<p><img src=\"https://img-blog.csdnimg.cn/2020041800180515.png?x-oss-process=image/watermark,type_ZmFuZ3poZW5naGVpdGk,shadow_10,text_aHR0cHM6Ly9ibG9nLmNzZG4ubmV0L1RyaURpYW1vbmQ2,size_16,color_FFFFFF,t_70\" alt=\"在这里插入图片描述\"></p>\n<p><img src=\"https://imgconvert.csdnimg.cn/aHR0cHM6Ly91c2VyLWdvbGQtY2RuLnhpdHUuaW8vMjAyMC80LzExLzE3MTY4NzdiNmRhMzMzNGM?x-oss-process=image/format,png\"></p>\n<h1 id=\"「三」图标主题集合\"><a href=\"#「三」图标主题集合\" class=\"headerlink\" title=\"「三」图标主题集合\"></a>「三」图标主题集合</h1><p>安装了编辑器主题，不安装图标主题就等同于 💐 鲜花插在了 💩 牛粪上。这里推荐两款我自己使用过的图标主题。</p>\n<p><img src=\"https://imgconvert.csdnimg.cn/aHR0cHM6Ly91c2VyLWdvbGQtY2RuLnhpdHUuaW8vMjAyMC80LzEyLzE3MTZkMWNjMDhjNTA1NDM?x-oss-process=image/format,png\"></p>\n<h2 id=\"Material-Icon-Theme\"><a href=\"#Material-Icon-Theme\" class=\"headerlink\" title=\"Material Icon Theme\"></a>Material Icon Theme</h2><p><code>主题名：Material Icon Theme</code></p>\n<p>占了大部分人都是用这个图标主题，内含非常齐全的图标，基本你能想到的文件都在内了。非常推荐使用！</p>\n<p><img src=\"https://img-blog.csdnimg.cn/20200418002457384.png?x-oss-process=image/watermark,type_ZmFuZ3poZW5naGVpdGk,shadow_10,text_aHR0cHM6Ly9ibG9nLmNzZG4ubmV0L1RyaURpYW1vbmQ2,size_16,color_FFFFFF,t_70\"></p>\n<p><img src=\"https://imgconvert.csdnimg.cn/aHR0cHM6Ly91c2VyLWdvbGQtY2RuLnhpdHUuaW8vMjAyMC80LzEyLzE3MTZkMWNjMDhjNTA1NDM?x-oss-process=image/format,png\"></p>\n<h2 id=\"VSCode-Icons\"><a href=\"#VSCode-Icons\" class=\"headerlink\" title=\"VSCode Icons\"></a>VSCode Icons</h2><p><code>主题名：vscode-icons</code></p>\n<p>这一款是 VSCode 官方的图标主题包，有超过 500 万+下载量。可以说是和 Material Icon 一样占了另外一大部分人在使用的一款主题。看个人喜好选择使用。个人觉得两款最大的区别在于文件夹。但是觉得 Material Icon 做的图标相对更加协调一些。</p>\n<p><img src=\"https://img-blog.csdnimg.cn/20200418003022696.gif\"></p>\n<p><img src=\"https://imgconvert.csdnimg.cn/aHR0cHM6Ly91c2VyLWdvbGQtY2RuLnhpdHUuaW8vMjAyMC80LzExLzE3MTY4NzdiNmRhMzMzNGM?x-oss-process=image/format,png\"></p>\n<h1 id=\"「四」实用插件集合\"><a href=\"#「四」实用插件集合\" class=\"headerlink\" title=\"「四」实用插件集合\"></a>「四」实用插件集合</h1><p>这里给小伙伴们介绍一些在其他 IDE 都有可能用过的超级实用插件和功能。这些插件主要是强化编辑器的功能，让我们在开发过程中得到非常大的帮助。</p>\n<p><img src=\"https://imgconvert.csdnimg.cn/aHR0cHM6Ly91c2VyLWdvbGQtY2RuLnhpdHUuaW8vMjAyMC80LzEyLzE3MTZkMWNjMDhjNTA1NDM?x-oss-process=image/format,png\"></p>\n<h2 id=\"代码书签\"><a href=\"#代码书签\" class=\"headerlink\" title=\"代码书签\"></a>代码书签</h2><p><code>插件名：Bookmarks</code></p>\n<p>它是代码中导航，在重要位置之间轻松快速地移动。不再需要搜索代码。它还支持一组选择命令，允许我们选择书签行和书签行之间的区域。它对于日志文件分析非常有用。</p>\n<p>以下是书签提供的一些功能:</p>\n<ul>\n<li>在代码中标记&#x2F;取消标记位置</li>\n<li>在代码中标记位置并给出名称</li>\n<li>在书签之间来回跳转</li>\n<li>查看一个文件中所有书签的列表</li>\n<li>查看项目中所有书签的列表</li>\n<li>专用侧杆</li>\n<li>带有书签的行</li>\n<li>选择书签之间的区域</li>\n</ul>\n<p><img src=\"https://img-blog.csdnimg.cn/20200418012741399.png?x-oss-process=image/watermark,type_ZmFuZ3poZW5naGVpdGk,shadow_10,text_aHR0cHM6Ly9ibG9nLmNzZG4ubmV0L1RyaURpYW1vbmQ2,size_16,color_FFFFFF,t_70\"></p>\n<p>这里附上我经常使用的几个这个插件的命令：</p>\n<ul>\n<li><code>Bookmarks: List</code> 列出当前文件中的所有书签</li>\n<li><code>Bookmarks: List from All Files</code> 列出当前项目下所有书签</li>\n<li><code>Bookmarks: Clear</code> 删除当前文件中的所有书签</li>\n<li><code>Bookmarks: Clear from All Files</code> 删除当前项目下的所有书签</li>\n</ul>\n<p>我们还可以通过打开侧边栏中的书签 tab 查看所有标签：<br><img src=\"https://img-blog.csdnimg.cn/20200418012716801.png?x-oss-process=image/watermark,type_ZmFuZ3poZW5naGVpdGk,shadow_10,text_aHR0cHM6Ly9ibG9nLmNzZG4ubmV0L1RyaURpYW1vbmQ2,size_16,color_FFFFFF,t_70\"></p>\n<p><img src=\"https://imgconvert.csdnimg.cn/aHR0cHM6Ly91c2VyLWdvbGQtY2RuLnhpdHUuaW8vMjAyMC80LzEyLzE3MTZkMWNjMDhjNTA1NDM?x-oss-process=image/format,png\"></p>\n<h2 id=\"括号对彩色化\"><a href=\"#括号对彩色化\" class=\"headerlink\" title=\"括号对彩色化\"></a>括号对彩色化</h2><p><code>插件名：Bracket Pair Colorizer 2</code></p>\n<p>这个扩展使用颜色来标识匹配的括号。用户可以定义要如何匹配，以及要使用哪些颜色。在代码量比较多的情况下，括号也会变得非常的多，有了颜色的标识会给开发者带来更好的识别能力。</p>\n<p><img src=\"https://img-blog.csdnimg.cn/20200418014147718.png?x-oss-process=image/watermark,type_ZmFuZ3poZW5naGVpdGk,shadow_10,text_aHR0cHM6Ly9ibG9nLmNzZG4ubmV0L1RyaURpYW1vbmQ2,size_16,color_FFFFFF,t_70\"></p>\n<p><img src=\"https://imgconvert.csdnimg.cn/aHR0cHM6Ly91c2VyLWdvbGQtY2RuLnhpdHUuaW8vMjAyMC80LzEyLzE3MTZkMWNjMDhjNTA1NDM?x-oss-process=image/format,png\"></p>\n<h2 id=\"增强-Git-功能\"><a href=\"#增强-Git-功能\" class=\"headerlink\" title=\"增强 Git 功能\"></a>增强 Git 功能</h2><p><code>插件名：GitLens</code></p>\n<p>增强 VSCode 中内置的 Git 功能——通过 Git blame 注释和代码透镜，一眼就能看到代码作者的身份，无缝导航和探索 Git 存储库，通过强大的比较命令获得有价值的见解，等等。<code>使用Git代码管理的开发者们，这个是一个必装插件之一！</code></p>\n<p><img src=\"https://img-blog.csdnimg.cn/2020041811220153.png?x-oss-process=image/watermark,type_ZmFuZ3poZW5naGVpdGk,shadow_10,text_aHR0cHM6Ly9ibG9nLmNzZG4ubmV0L1RyaURpYW1vbmQ2,size_16,color_FFFFFF,t_70\"></p>\n<p><img src=\"https://imgconvert.csdnimg.cn/aHR0cHM6Ly91c2VyLWdvbGQtY2RuLnhpdHUuaW8vMjAyMC80LzEyLzE3MTZkMWNjMDhjNTA1NDM?x-oss-process=image/format,png\"></p>\n<h2 id=\"Git-历史记录\"><a href=\"#Git-历史记录\" class=\"headerlink\" title=\"Git 历史记录\"></a>Git 历史记录</h2><p><code>插件名：Git History</code></p>\n<p>对于一些开发者习惯使用编辑器中的 Git 管理工具的，不太喜欢要打开另外一个 Git UI 工具的同学，这一款插件满足你查询所有 Git 记录的需求。</p>\n<ul>\n<li>查看和搜索 git 日志中的图形和详细信息。</li>\n<li>查看文件以前的副本。</li>\n<li>查看和搜索历史</li>\n<li>比较分支&#x2F;提交记录&#x2F;文件</li>\n<li>更多～</li>\n</ul>\n<p><img src=\"https://img-blog.csdnimg.cn/20200418111356920.gif\"></p>\n<p><img src=\"https://imgconvert.csdnimg.cn/aHR0cHM6Ly91c2VyLWdvbGQtY2RuLnhpdHUuaW8vMjAyMC80LzEyLzE3MTZkMWNjMDhjNTA1NDM?x-oss-process=image/format,png\"></p>\n<h2 id=\"实时协作编辑\"><a href=\"#实时协作编辑\" class=\"headerlink\" title=\"实时协作编辑\"></a>实时协作编辑</h2><p><code>插件名：Live Share</code></p>\n<p>Visual Studio Live Share 允许我们与他人实时协作编辑和调试，不管我们使用的是哪种编程语言或正在构建的应用程序类型。它允许我们立即(并且安全地)共享我们当前的项目，然后根据需要共享调试会话、终端实例、本地主机 web 应用程序、语音呼叫等等！加入我们的会话的开发人员从我们的环境中接收所有的编辑器上下文(例如，语言服务、调试)，这确保了他们可以立即开始有效地协作，而不需要克隆任何代码或安装任何 sdk。</p>\n<p>此外，与传统的结对编程不同，Visual Studio Live Share 允许开发人员一起工作，同时保留他们的个人编辑器首选项(例如主题、键绑定)，以及拥有自己的游标。这允许我们在跟随他人和自己探索想法&#x2F;任务之间无缝过渡。在实践中，这种协作和独立工作的能力为许多常见用例提供了一种更自然的协作体验。</p>\n<p><img src=\"https://img-blog.csdnimg.cn/20200418121855294.png?x-oss-process=image/watermark,type_ZmFuZ3poZW5naGVpdGk,shadow_10,text_aHR0cHM6Ly9ibG9nLmNzZG4ubmV0L1RyaURpYW1vbmQ2,size_16,color_FFFFFF,t_70\"></p>\n<p>要使用这个协同软件，首先我们需要登陆（推荐使用 GitHub 登陆）。登陆后点击下方的<code>Live Share</code>:</p>\n<p><img src=\"https://img-blog.csdnimg.cn/20200418122107913.png?x-oss-process=image/watermark,type_ZmFuZ3poZW5naGVpdGk,shadow_10,text_aHR0cHM6Ly9ibG9nLmNzZG4ubmV0L1RyaURpYW1vbmQ2,size_16,color_FFFFFF,t_70\"></p>\n<p>然后编辑器就会弹出以下提示，具体意思就是说，我们的实时共享会话已经开启，邀请连接已经被复制，可以发给你的协助开发者。</p>\n<p><img src=\"https://img-blog.csdnimg.cn/20200418122225281.png?x-oss-process=image/watermark,type_ZmFuZ3poZW5naGVpdGk,shadow_10,text_aHR0cHM6Ly9ibG9nLmNzZG4ubmV0L1RyaURpYW1vbmQ2,size_16,color_FFFFFF,t_70\"></p>\n<p>这个时候我们可以把连接发给我们的协助者，这里对方必须安装了<code>Live Share</code>的插件并且必须是登陆状态。</p>\n<p>这个时候对方只需要点击侧边栏的<code>Live Share</code>图标，然后在<code>会话详细信息</code>中找到并且点击<code>加入协作会话...</code>。</p>\n<p>点击后编辑器上方会出现一个输入框，对方只需要输入我们提供的邀请连接然后按回车即可。</p>\n<p><img src=\"https://img-blog.csdnimg.cn/20200418122652558.png?x-oss-process=image/watermark,type_ZmFuZ3poZW5naGVpdGk,shadow_10,text_aHR0cHM6Ly9ibG9nLmNzZG4ubmV0L1RyaURpYW1vbmQ2,size_16,color_FFFFFF,t_70\"></p>\n<p>协助完毕后，我们可以点击下方的图中的图标<br><img src=\"https://img-blog.csdnimg.cn/20200418122944492.png?x-oss-process=image/watermark,type_ZmFuZ3poZW5naGVpdGk,shadow_10,text_aHR0cHM6Ly9ibG9nLmNzZG4ubmV0L1RyaURpYW1vbmQ2,size_16,color_FFFFFF,t_70\"><br>点击图标后，上方会出现一个选择弹窗，选择<code>Stop Collaboration Session</code>就可以停止协助会话了。<br><img src=\"https://img-blog.csdnimg.cn/20200418123003827.png?x-oss-process=image/watermark,type_ZmFuZ3poZW5naGVpdGk,shadow_10,text_aHR0cHM6Ly9ibG9nLmNzZG4ubmV0L1RyaURpYW1vbmQ2,size_16,color_FFFFFF,t_70\"></p>\n<p><img src=\"https://imgconvert.csdnimg.cn/aHR0cHM6Ly91c2VyLWdvbGQtY2RuLnhpdHUuaW8vMjAyMC80LzEyLzE3MTZkMWNjMDhjNTA1NDM?x-oss-process=image/format,png\"></p>\n<h2 id=\"路径智能提示\"><a href=\"#路径智能提示\" class=\"headerlink\" title=\"路径智能提示\"></a>路径智能提示</h2><p><code>插件名：Path Intellisense</code></p>\n<p>加入此插件让我们在应用文件（例如图片）时，有智能的路径提示。</p>\n<p><img src=\"https://img-blog.csdnimg.cn/20200418153346888.png?x-oss-process=image/watermark,type_ZmFuZ3poZW5naGVpdGk,shadow_10,text_aHR0cHM6Ly9ibG9nLmNzZG4ubmV0L1RyaURpYW1vbmQ2,size_16,color_FFFFFF,t_70\"></p>\n<p><img src=\"https://imgconvert.csdnimg.cn/aHR0cHM6Ly91c2VyLWdvbGQtY2RuLnhpdHUuaW8vMjAyMC80LzExLzE3MTY4NzdiNmRhMzMzNGM?x-oss-process=image/format,png\"></p>\n<h1 id=\"「五」前端开发插件集合\"><a href=\"#「五」前端开发插件集合\" class=\"headerlink\" title=\"「五」前端开发插件集合\"></a>「五」前端开发插件集合</h1><p>这里提供给各位童鞋世上最全的前端开发插件集合，没有“之一”。（当然要做到最强还需要大家给我多提意见，欢迎小伙伴们给我补充一些我也还没有使用过的实用前端插件哦！可以在评论区留言哈！）</p>\n<p>程序员最好的朋友无非就是编辑器中的插件，有插件和没有使用插件在开发中简直就是天差地别。这里让我想到自己一开始学习编程的时候，使用<code>notepad++</code>，一行一行代码纯手敲的经历。现在有了各式各样的 IDE，估计已经差不多没有人还在用文本编辑器手敲代码了。</p>\n<p><img src=\"https://imgconvert.csdnimg.cn/aHR0cHM6Ly91c2VyLWdvbGQtY2RuLnhpdHUuaW8vMjAyMC80LzEyLzE3MTZkMWNjMDhjNTA1NDM?x-oss-process=image/format,png\"></p>\n<h2 id=\"自动关闭标签\"><a href=\"#自动关闭标签\" class=\"headerlink\" title=\"自动关闭标签\"></a>自动关闭标签</h2><p><code>插件名：Auto Close Tag</code></p>\n<p>自动添加<code>HTML/XML</code>关闭标签，与 Visual Studio IDE 或 SublimeText 相同。当我们填写了开始标签，结束标签就会被自动加上。这个非常实用，减少很多我们写<code>html</code>和<code>xml</code>的时间。</p>\n<p><img src=\"https://img-blog.csdnimg.cn/20200418005726730.gif\"></p>\n<p>如果是使用<code>SublimeText</code>过来的或者习惯<code>SublimeText</code>的童鞋，可以开启<code>Sublime Text 3模式</code>，在<code>settings.json</code>文件里面加入这个配置：</p>\n<pre class=\"line-numbers language-json\" data-language=\"json\"><code class=\"language-json\">&#123;\n  &quot;auto-close-tag.SublimeText3Mode&quot;: true\n&#125;</code></pre>\n\n<p><img src=\"https://img-blog.csdnimg.cn/20200418010218218.gif\"></p>\n<p><img src=\"https://imgconvert.csdnimg.cn/aHR0cHM6Ly91c2VyLWdvbGQtY2RuLnhpdHUuaW8vMjAyMC80LzEyLzE3MTZkMWNjMDhjNTA1NDM?x-oss-process=image/format,png\"></p>\n<h2 id=\"自动同步标签名\"><a href=\"#自动同步标签名\" class=\"headerlink\" title=\"自动同步标签名\"></a>自动同步标签名</h2><p><code>插件名：Auto Rename Tag</code></p>\n<p>自动重命名成对的 HTML&#x2F;XML 标记，与 Visual Studio IDE 相同。用这个插件可以告别每次改变标签的时候要重复修改头部和尾部标签。特别是标签内内容非常多的时候，要改确实很费劲的。</p>\n<p><img src=\"https://img-blog.csdnimg.cn/2020041801062749.gif\"></p>\n<p><img src=\"https://imgconvert.csdnimg.cn/aHR0cHM6Ly91c2VyLWdvbGQtY2RuLnhpdHUuaW8vMjAyMC80LzEyLzE3MTZkMWNjMDhjNTA1NDM?x-oss-process=image/format,png\"></p>\n<h2 id=\"CSS-颜色高亮\"><a href=\"#CSS-颜色高亮\" class=\"headerlink\" title=\"CSS 颜色高亮\"></a>CSS 颜色高亮</h2><p><code>插件名：Color Highlight</code></p>\n<p>这个插件会对页面上所有的 CSS&#x2F;web 的颜色编码进行高亮，高亮的颜色就是编码对应的颜色。在写 CSS 的时候非常实用。</p>\n<p><img src=\"https://img-blog.csdnimg.cn/2020041810433844.png?x-oss-process=image/watermark,type_ZmFuZ3poZW5naGVpdGk,shadow_10,text_aHR0cHM6Ly9ibG9nLmNzZG4ubmV0L1RyaURpYW1vbmQ2,size_16,color_FFFFFF,t_70\"></p>\n<p><img src=\"https://imgconvert.csdnimg.cn/aHR0cHM6Ly91c2VyLWdvbGQtY2RuLnhpdHUuaW8vMjAyMC80LzEyLzE3MTZkMWNjMDhjNTA1NDM?x-oss-process=image/format,png\"></p>\n<h2 id=\"高亮匹对标签\"><a href=\"#高亮匹对标签\" class=\"headerlink\" title=\"高亮匹对标签\"></a>高亮匹对标签</h2><p><code>插件名：VSCode Highlight Matching Tag</code></p>\n<p>此插件高亮显示匹对的开始和&#x2F;或结束标签。还可以在状态栏中显示标签的路径。这个插件将尝试在任何地方匹配标记: 从标记属性、字符串内部、任何文件，同时还提供广泛的样式选项来定制标记的高亮显示方式。</p>\n<p>官方支持的标签: HTML 和 JSX。其他风格 (XML、Vue、Angular、PHP) 也可以。</p>\n<p><img src=\"https://img-blog.csdnimg.cn/2020041811313577.png?x-oss-process=image/watermark,type_ZmFuZ3poZW5naGVpdGk,shadow_10,text_aHR0cHM6Ly9ibG9nLmNzZG4ubmV0L1RyaURpYW1vbmQ2,size_16,color_FFFFFF,t_70\"></p>\n<p><img src=\"https://imgconvert.csdnimg.cn/aHR0cHM6Ly91c2VyLWdvbGQtY2RuLnhpdHUuaW8vMjAyMC80LzEyLzE3MTZkMWNjMDhjNTA1NDM?x-oss-process=image/format,png\"></p>\n<h2 id=\"HTML-CSS-支持\"><a href=\"#HTML-CSS-支持\" class=\"headerlink\" title=\"HTML CSS 支持\"></a>HTML CSS 支持</h2><p><code>插件名：HTML CSS Support</code></p>\n<p>补充了 VSCode 中缺少的 CSS 支持。类属性补全、ID 属性补全和全文件搜索 CSS 和 SCSS 提示等。</p>\n<p><img src=\"https://img-blog.csdnimg.cn/20200418120102528.png?x-oss-process=image/watermark,type_ZmFuZ3poZW5naGVpdGk,shadow_10,text_aHR0cHM6Ly9ibG9nLmNzZG4ubmV0L1RyaURpYW1vbmQ2,size_16,color_FFFFFF,t_70\"></p>\n<p><img src=\"https://imgconvert.csdnimg.cn/aHR0cHM6Ly91c2VyLWdvbGQtY2RuLnhpdHUuaW8vMjAyMC80LzEyLzE3MTZkMWNjMDhjNTA1NDM?x-oss-process=image/format,png\"></p>\n<h2 id=\"小程序支持\"><a href=\"#小程序支持\" class=\"headerlink\" title=\"小程序支持\"></a>小程序支持</h2><p><code>插件名：minapp-vscode</code></p>\n<p>微信小程序标签、属性的智能补全（同时支持原生小程序、mpvue 和 wepy 框架，并提供 snippets）</p>\n<p><img src=\"https://img-blog.csdnimg.cn/20200418124310840.gif\"></p>\n<p><img src=\"https://imgconvert.csdnimg.cn/aHR0cHM6Ly91c2VyLWdvbGQtY2RuLnhpdHUuaW8vMjAyMC80LzEyLzE3MTZkMWNjMDhjNTA1NDM?x-oss-process=image/format,png\"></p>\n<h2 id=\"Vue-支持\"><a href=\"#Vue-支持\" class=\"headerlink\" title=\"Vue 支持\"></a>Vue 支持</h2><p><code>插件名：Vetur</code></p>\n<p>开发 Vue 的童鞋必装插件之一。支持标签、属性的智能补全等等。</p>\n<p><img src=\"https://img-blog.csdnimg.cn/20200418133244365.png?x-oss-process=image/watermark,type_ZmFuZ3poZW5naGVpdGk,shadow_10,text_aHR0cHM6Ly9ibG9nLmNzZG4ubmV0L1RyaURpYW1vbmQ2,size_16,color_FFFFFF,t_70\"></p>\n<p>经常用 Vue 开发的童鞋，我这个里另外推荐一个插件给你们。就是<code>Vue 2 Snippets</code>，这个插件加入了 Vue2 的代码块，让我们开发的过程中可以快速生成 Vue2 的代模版。</p>\n<p><img src=\"https://img-blog.csdnimg.cn/20200418191201486.png?x-oss-process=image/watermark,type_ZmFuZ3poZW5naGVpdGk,shadow_10,text_aHR0cHM6Ly9ibG9nLmNzZG4ubmV0L1RyaURpYW1vbmQ2,size_16,color_FFFFFF,t_70\" alt=\"在这里插入图片描述\"></p>\n<p><img src=\"https://imgconvert.csdnimg.cn/aHR0cHM6Ly91c2VyLWdvbGQtY2RuLnhpdHUuaW8vMjAyMC80LzEyLzE3MTZkMWNjMDhjNTA1NDM?x-oss-process=image/format,png\"></p>\n<h2 id=\"React-支持\"><a href=\"#React-支持\" class=\"headerlink\" title=\"React 支持\"></a>React 支持</h2><p><code>插件名：ES7 React/Redux/GraphQL/React-Native snippets</code></p>\n<p>这个扩展为你提供了 JavaScript 和 ES7 中的 React&#x2F;Redux 代码片段，以及 VSCode 的 Babel 插件特性。编写 React 的童鞋，这个插件是必备之一。<br><img src=\"https://img-blog.csdnimg.cn/20200418152134991.png?x-oss-process=image/watermark,type_ZmFuZ3poZW5naGVpdGk,shadow_10,text_aHR0cHM6Ly9ibG9nLmNzZG4ubmV0L1RyaURpYW1vbmQ2,size_16,color_FFFFFF,t_70\" alt=\"在这里插入图片描述\"></p>\n<p><img src=\"https://imgconvert.csdnimg.cn/aHR0cHM6Ly91c2VyLWdvbGQtY2RuLnhpdHUuaW8vMjAyMC80LzEyLzE3MTZkMWNjMDhjNTA1NDM?x-oss-process=image/format,png\"></p>\n<h2 id=\"NPM-支持\"><a href=\"#NPM-支持\" class=\"headerlink\" title=\"NPM 支持\"></a>NPM 支持</h2><p><code>插件名：npm</code></p>\n<p>这个扩展支持运行包中定义的 npm 脚本。并根据包中定义的依赖项验证已安装的模块。最喜欢这个插件的功能就是可以自动检测依赖是否安装，还可以提示依赖的版本和具体项目地址。使用 npm 的童鞋必备插件之一。</p>\n<p><img src=\"https://img-blog.csdnimg.cn/20200418152519394.png?x-oss-process=image/watermark,type_ZmFuZ3poZW5naGVpdGk,shadow_10,text_aHR0cHM6Ly9ibG9nLmNzZG4ubmV0L1RyaURpYW1vbmQ2,size_16,color_FFFFFF,t_70\"></p>\n<p><img src=\"https://imgconvert.csdnimg.cn/aHR0cHM6Ly91c2VyLWdvbGQtY2RuLnhpdHUuaW8vMjAyMC80LzEyLzE3MTZkMWNjMDhjNTA1NDM?x-oss-process=image/format,png\"></p>\n<h2 id=\"NPM-智能提示\"><a href=\"#NPM-智能提示\" class=\"headerlink\" title=\"NPM 智能提示\"></a>NPM 智能提示</h2><p><code>插件名：npm Intellisense</code></p>\n<p>加入此插件可以让我们在编写 JavaScript 的时候有 npm 依赖包的提示。特别是引用的过程中会有丰富的提示。</p>\n<p><img src=\"https://img-blog.csdnimg.cn/20200418152750763.gif\"></p>\n<p><img src=\"https://imgconvert.csdnimg.cn/aHR0cHM6Ly91c2VyLWdvbGQtY2RuLnhpdHUuaW8vMjAyMC80LzEyLzE3MTZkMWNjMDhjNTA1NDM?x-oss-process=image/format,png\"></p>\n<h2 id=\"强大的代码格式化\"><a href=\"#强大的代码格式化\" class=\"headerlink\" title=\"强大的代码格式化\"></a>强大的代码格式化</h2><p><code>插件名：Prettier - Code formatter</code></p>\n<p>Prettier 是一个代码格式化程序。它通过解析代码并使用它自己的规则重新打印代码来强制实现一致的样式，这些规则考虑到最大行长度，在必要时包装代码。</p>\n<p>在一个多人协同开发的团队中，统一的代码编写规范非常重要。一套规范可以让我们编写的代码达到一致的风格，提高代码的可读性和统一性。自然维护性也会有所提高。</p>\n<p><img src=\"https://img-blog.csdnimg.cn/20200418154244795.gif\"></p>\n<blockquote><span class=\"custom-blockquote-svg\"><svg width=\"24\" height=\"24\" viewBox=\"0 0 24 24\" fill=\"\" xmlns=\"http://www.w3.org/2000/svg\" data-reactroot=\"\">\n<path fill=\"\" d=\"M22 12C22 6.5 17.5 2 12 2C6.5 2 2 6.5 2 12C2 17.5 6.5 22 12 22C13.8 22 15.5 21.5 17 20.6L22 22L20.7 17C21.5 15.5 22 13.8 22 12Z\" undefined=\"1\"></path>\n<path fill=\"\" d=\"M15.97 11.5H16.04C17.12 11.5 18 12.38 18 13.47V13.53C18 14.62 17.12 15.5 16.03 15.5H15.96C14.88 15.5 14 14.62 14 13.53V13.46C14 12.38 14.88 11.5 15.97 11.5Z\" undefined=\"1\"></path>\n<path fill=\"\" d=\"M7.97 11.5H8.04C9.12 11.5 10 12.38 10 13.47V13.53C10 14.62 9.12 15.5 8.03 15.5H7.97C6.88 15.5 6 14.62 6 13.53V13.46C6 12.38 6.88 11.5 7.97 11.5Z\" undefined=\"1\"></path>\n<path stroke-linejoin=\"round\" stroke-linecap=\"round\" stroke-miterlimit=\"10\" stroke-width=\"2\" stroke=\"\" d=\"M17 8.5C15.23 8.97 14.07 10.84 14.01 13.27C14 13.33 14 13.4 14 13.47V13.5\"></path>\n<path stroke-linejoin=\"round\" stroke-linecap=\"round\" stroke-miterlimit=\"10\" stroke-width=\"2\" stroke=\"\" d=\"M9 8.5C7.23 8.97 6.07 10.84 6.01 13.27C6 13.33 6 13.4 6 13.47V13.5\"></path>\n<path stroke-linejoin=\"round\" stroke-linecap=\"round\" stroke-miterlimit=\"10\" stroke-width=\"2\" stroke=\"\" d=\"M15.97 11.5H16.04C17.12 11.5 18 12.38 18 13.47V13.53C18 14.62 17.12 15.5 16.03 15.5H15.96C14.88 15.5 14 14.62 14 13.53V13.46C14 12.38 14.88 11.5 15.97 11.5Z\"></path>\n<path stroke-linejoin=\"round\" stroke-linecap=\"round\" stroke-miterlimit=\"10\" stroke-width=\"2\" stroke=\"\" d=\"M7.97 11.5H8.04C9.12 11.5 10 12.38 10 13.47V13.53C10 14.62 9.12 15.5 8.03 15.5H7.97C6.88 15.5 6 14.62 6 13.53V13.46C6 12.38 6.88 11.5 7.97 11.5Z\"></path>\n</svg>\n</span><p>🌟 小技巧<br>我们可以通过在<code>settings.json</code>中强制让一些特定语言用这个格式化工具。在<code>settings.json</code>中添加以下配置。</p></blockquote>\n<pre class=\"line-numbers language-json\" data-language=\"json\"><code class=\"language-json\">&#123;\n  &quot;editor.defaultFormatter&quot;: &quot;esbenp.prettier-vscode&quot;,\n  &quot;[javascript]&quot;: &#123;\n    &quot;editor.defaultFormatter&quot;: &quot;esbenp.prettier-vscode&quot;\n  &#125;\n&#125;</code></pre>\n\n<blockquote><span class=\"custom-blockquote-svg\"><svg width=\"24\" height=\"24\" viewBox=\"0 0 24 24\" fill=\"\" xmlns=\"http://www.w3.org/2000/svg\" data-reactroot=\"\">\n<path fill=\"\" d=\"M22 12C22 6.5 17.5 2 12 2C6.5 2 2 6.5 2 12C2 17.5 6.5 22 12 22C13.8 22 15.5 21.5 17 20.6L22 22L20.7 17C21.5 15.5 22 13.8 22 12Z\" undefined=\"1\"></path>\n<path fill=\"\" d=\"M15.97 11.5H16.04C17.12 11.5 18 12.38 18 13.47V13.53C18 14.62 17.12 15.5 16.03 15.5H15.96C14.88 15.5 14 14.62 14 13.53V13.46C14 12.38 14.88 11.5 15.97 11.5Z\" undefined=\"1\"></path>\n<path fill=\"\" d=\"M7.97 11.5H8.04C9.12 11.5 10 12.38 10 13.47V13.53C10 14.62 9.12 15.5 8.03 15.5H7.97C6.88 15.5 6 14.62 6 13.53V13.46C6 12.38 6.88 11.5 7.97 11.5Z\" undefined=\"1\"></path>\n<path stroke-linejoin=\"round\" stroke-linecap=\"round\" stroke-miterlimit=\"10\" stroke-width=\"2\" stroke=\"\" d=\"M17 8.5C15.23 8.97 14.07 10.84 14.01 13.27C14 13.33 14 13.4 14 13.47V13.5\"></path>\n<path stroke-linejoin=\"round\" stroke-linecap=\"round\" stroke-miterlimit=\"10\" stroke-width=\"2\" stroke=\"\" d=\"M9 8.5C7.23 8.97 6.07 10.84 6.01 13.27C6 13.33 6 13.4 6 13.47V13.5\"></path>\n<path stroke-linejoin=\"round\" stroke-linecap=\"round\" stroke-miterlimit=\"10\" stroke-width=\"2\" stroke=\"\" d=\"M15.97 11.5H16.04C17.12 11.5 18 12.38 18 13.47V13.53C18 14.62 17.12 15.5 16.03 15.5H15.96C14.88 15.5 14 14.62 14 13.53V13.46C14 12.38 14.88 11.5 15.97 11.5Z\"></path>\n<path stroke-linejoin=\"round\" stroke-linecap=\"round\" stroke-miterlimit=\"10\" stroke-width=\"2\" stroke=\"\" d=\"M7.97 11.5H8.04C9.12 11.5 10 12.38 10 13.47V13.53C10 14.62 9.12 15.5 8.03 15.5H7.97C6.88 15.5 6 14.62 6 13.53V13.46C6 12.38 6.88 11.5 7.97 11.5Z\"></path>\n</svg>\n</span><p>🌟 小技巧<br>个人还建议设置编辑器在保存时自动格式化。在<code>settings.json</code>中添加以下配置。</p></blockquote>\n<pre class=\"line-numbers language-json\" data-language=\"json\"><code class=\"language-json\">&#x2F;&#x2F; 全局配置\n&quot;editor.formatOnSave&quot;: false,\n&#x2F;&#x2F; 按语言配置\n&quot;[javascript]&quot;: &#123;\n    &quot;editor.formatOnSave&quot;: true\n&#125;</code></pre>\n\n<p><img src=\"https://imgconvert.csdnimg.cn/aHR0cHM6Ly91c2VyLWdvbGQtY2RuLnhpdHUuaW8vMjAyMC80LzEyLzE3MTZkMWNjMDhjNTA1NDM?x-oss-process=image/format,png\"></p>\n<h2 id=\"编辑器中的实时预览\"><a href=\"#编辑器中的实时预览\" class=\"headerlink\" title=\"编辑器中的实时预览\"></a>编辑器中的实时预览</h2><p><code>插件名：Browser Preview</code></p>\n<p>VSCode 的浏览器预览插件让我们能够在编辑器中打开一个可以真正的浏览器预览。浏览器预览是由 Chrome Headless 提供的，它的工作原理是在一个新进程中启动一个 Headless Chrome 实例。提供了一种安全的方法在 VSCode 中呈现 web 内容，并支持一些有趣的特性，如编辑器内调试等! <code>再也不用在浏览器和编辑器中来回切换而觉得麻烦了！</code></p>\n<p><img src=\"https://img-blog.csdnimg.cn/20200418103219207.gif\" alt=\"在这里插入图片描述\"></p>\n<p>这个插件需要另外一个插件的支持<code>Debugger for Chrome</code>，安装了这个插件后只要按下面配置格式配置即可（配置要根据我们的项目而定，需要微小的修改一下）</p>\n<pre class=\"line-numbers language-json\" data-language=\"json\"><code class=\"language-json\">&#123;\n  &quot;version&quot;: &quot;0.1.0&quot;,\n  &quot;configurations&quot;: [\n    &#123;\n      &quot;type&quot;: &quot;browser-preview&quot;,\n      &quot;request&quot;: &quot;attach&quot;,\n      &quot;name&quot;: &quot;Browser Preview: Attach&quot;\n    &#125;,\n    &#123;\n      &quot;type&quot;: &quot;browser-preview&quot;,\n      &quot;request&quot;: &quot;launch&quot;,\n      &quot;name&quot;: &quot;Browser Preview: Launch&quot;,\n      &quot;url&quot;: &quot;http:&#x2F;&#x2F;localhost:3000&quot; &#x2F;&#x2F; 把这里改为你本地项目的地址\n    &#125;\n  ]\n&#125;</code></pre>\n\n<p><img src=\"https://imgconvert.csdnimg.cn/aHR0cHM6Ly91c2VyLWdvbGQtY2RuLnhpdHUuaW8vMjAyMC80LzEyLzE3MTZkMWNjMDhjNTA1NDM?x-oss-process=image/format,png\"></p>\n<h2 id=\"实时预览\"><a href=\"#实时预览\" class=\"headerlink\" title=\"实时预览\"></a>实时预览</h2><p><code>插件名：Live Server</code></p>\n<p>如果我们是在做一个静态页排版，这个插件可以提供给我们一个本地实时预览服务器，预览会在谷歌浏览器打开。相对于上面讲到的插件来说，这个比较轻量级。</p>\n<p><img src=\"https://img-blog.csdnimg.cn/20200418120711117.gif\"></p>\n<p><img src=\"https://imgconvert.csdnimg.cn/aHR0cHM6Ly91c2VyLWdvbGQtY2RuLnhpdHUuaW8vMjAyMC80LzEyLzE3MTZkMWNjMDhjNTA1NDM?x-oss-process=image/format,png\"></p>\n<h2 id=\"浏览器打开\"><a href=\"#浏览器打开\" class=\"headerlink\" title=\"浏览器打开\"></a>浏览器打开</h2><p><code>插件名：open in browser</code></p>\n<p>在开发本地文件的时候，可以安装这个插件，然后用默认浏览器打开。当然可以设置我们喜爱的浏览器打开哦。<br><img src=\"https://img-blog.csdnimg.cn/20200418161247685.png?x-oss-process=image/watermark,type_ZmFuZ3poZW5naGVpdGk,shadow_10,text_aHR0cHM6Ly9ibG9nLmNzZG4ubmV0L1RyaURpYW1vbmQ2,size_16,color_FFFFFF,t_70\"></p>\n<p><img src=\"https://imgconvert.csdnimg.cn/aHR0cHM6Ly91c2VyLWdvbGQtY2RuLnhpdHUuaW8vMjAyMC80LzExLzE3MTY4NzdiNmRhMzMzNGM?x-oss-process=image/format,png\"></p>\n<h1 id=\"「六」PHP-开发插件\"><a href=\"#「六」PHP-开发插件\" class=\"headerlink\" title=\"「六」PHP 开发插件\"></a>「六」PHP 开发插件</h1><p>VSCode 作为前端开发编辑器确实很强大了，但是这个编辑器不仅限于前端，作为一个后端编辑器也不差于其他 IDE 很多。</p>\n<p>我有很长一段时间一直使用 PHPStorm，但是发现用再高配置的电脑还是逃不过这些重量级 IDE 对电脑的 CPU 和内存的无限吞噬。</p>\n<p>随着几款轻量级编辑器的发展，包括<code>SublimeText</code>、<code>Atom</code>和<code>VSCode</code>。这些轻量级的编辑器加上活跃的插件开发社区，很多在 IDE 里面拥有的功能在轻量级的编辑器中都可以拥有了。所以最后我又回归到了轻量级编辑器中。</p>\n<p>最后我开始研究怎么用 VSCode 作为 PHP 开发的 IDE。这里分享一些非常实用的 PHP 开发用的 VSCode 必装插件集合：</p>\n<p><img src=\"https://imgconvert.csdnimg.cn/aHR0cHM6Ly91c2VyLWdvbGQtY2RuLnhpdHUuaW8vMjAyMC80LzEyLzE3MTZkMWNjMDhjNTA1NDM?x-oss-process=image/format,png\"></p>\n<h2 id=\"PHP-强化插件\"><a href=\"#PHP-强化插件\" class=\"headerlink\" title=\"PHP 强化插件\"></a>PHP 强化插件</h2><p><code>插件名：PHP Intelephense</code></p>\n<p>PHP Intelephense 是一个高性能的 PHP 语言服务器，它为高效的 PHP 开发提供了大量的基本特性。安装了这个插件基本拥有了 70-80%重量级 IDE 的辅助功能。</p>\n<p>它的功能包含以下：</p>\n<ul>\n<li>快速驼峰&#x2F;下划线大小写**代码完成(智能感知)**。提供文档、项目和内置符号和关键字的详细提示。自动添加使用声明。</li>\n<li>项目和内置的构造函数，方法和函数都有详细<strong>签名(参数)帮助辅助</strong>。</li>\n<li>快速项目中的<strong>跳转定义</strong>支持。</li>\n<li>项目内<strong>查找所有引用</strong>。</li>\n<li><strong>项目内快速搜索</strong>“驼峰&#x2F;下划线”的符号</li>\n<li>完整<strong>文档符号搜索</strong>，也支持<strong>breadcrumb <strong>和</strong>outline</strong> UI。</li>\n<li>通过一个容错解析器和强大的静态分析引擎<strong>诊断</strong>打开的文件。</li>\n<li>兼容 PSR-12<strong>文档&#x2F;范围格式</strong>。格式化也适用于 HTML&#x2F;PHP&#x2F;JS&#x2F;CSS 文件。</li>\n<li>HTML 请求转发到 HTML 语言服务器完成<strong>HTML&#x2F;JS&#x2F;CSS&#x2F;PHP 代码智能提示</strong>。</li>\n<li><strong>鼠标悬停</strong>显示详细链接到官方 PHP 文档。</li>\n<li>智能<strong>高亮</strong>参考资料和关键字。</li>\n<li>读取<strong>PHPStorm metadata</strong>以获得更高级的类型分析和提示。</li>\n<li>智能<strong>重命名</strong>符号。在适当的时候，文件&#x2F;文件夹也会自动重命名。(高级版)(<a href=\"https://intelephense.com/\">https://intelephense.com</a>)</li>\n<li>能精确的<strong>折叠代码</strong>定义，块，使用声明，heredoc，注释，和自定义区域。(高级版)(<a href=\"https://intelephense.com/\">https://intelephense.com</a>)</li>\n<li>快速<strong>找到和跳转接口和抽象类以及相关方法</strong>。(高级版)(<a href=\"https://intelephense.com/\">https://intelephense.com</a>)</li>\n<li>快速<strong>转到类型定义</strong>的变量和参数。(高级版)(<a href=\"https://intelephense.com/\">https://intelephense.com</a>)</li>\n<li>快速<strong>去声明</strong>实现接口或抽象方法声明的方法。(高级版)(<a href=\"https://intelephense.com/\">https://intelephense.com</a>)</li>\n<li>可配置<strong>自动 phpdoc</strong>创建，推断返回类型并识别抛出的异常。(高级版)(<a href=\"https://intelephense.com/\">https://intelephense.com</a>)</li>\n</ul>\n<p>提到的<strong>高级版</strong>功能需要另外购买，可以到<code>https://intelephense.com</code>实用支付宝购买。一次性购买价格是 70 元人名币（个人觉得相比其他 IDE 是年费的，这个还是很划算的）。</p>\n<p>这个插件基本上所有其他 IDE 又的功能它都给你提供了，有了这个插件我们的 VSCode 瞬间编程了一个全能的 IDE 编辑器。重点它还是比较轻量级的。</p>\n<p><img src=\"https://img-blog.csdnimg.cn/20200418185139615.png?x-oss-process=image/watermark,type_ZmFuZ3poZW5naGVpdGk,shadow_10,text_aHR0cHM6Ly9ibG9nLmNzZG4ubmV0L1RyaURpYW1vbmQ2,size_16,color_FFFFFF,t_70\"></p>\n<p><img src=\"https://imgconvert.csdnimg.cn/aHR0cHM6Ly91c2VyLWdvbGQtY2RuLnhpdHUuaW8vMjAyMC80LzEyLzE3MTZkMWNjMDhjNTA1NDM?x-oss-process=image/format,png\"></p>\n<h2 id=\"PHP-规范检测\"><a href=\"#PHP-规范检测\" class=\"headerlink\" title=\"PHP 规范检测\"></a>PHP 规范检测</h2><p><code>插件名：phpcs</code></p>\n<p>这个 linter 插件为 Visual Studio 代码提供了一个到 phpc 的接口。它将与具有“PHP”语言模式的文件一起使用。</p>\n<p>如果小伙伴们一直都有用 linter，那这个插件装上，可以配合我们项目中的 phpCS 设置的 linter 一起用，就可以自动格式化代码或者在 VSCode 中也会提示格式错误了。</p>\n<p><img src=\"https://img-blog.csdnimg.cn/20200418185704744.png?x-oss-process=image/watermark,type_ZmFuZ3poZW5naGVpdGk,shadow_10,text_aHR0cHM6Ly9ibG9nLmNzZG4ubmV0L1RyaURpYW1vbmQ2,size_16,color_FFFFFF,t_70\"></p>\n<p><img src=\"https://imgconvert.csdnimg.cn/aHR0cHM6Ly91c2VyLWdvbGQtY2RuLnhpdHUuaW8vMjAyMC80LzExLzE3MTY4NzdiNmRhMzMzNGM?x-oss-process=image/format,png\"></p>\n<h1 id=\"「七」Java-开发插件\"><a href=\"#「七」Java-开发插件\" class=\"headerlink\" title=\"「七」Java 开发插件\"></a>「七」Java 开发插件</h1><p>个人没有做过多的 JAVA 开发，所以也没有深入研究，但是 VSCode 也有很多 Java 开发者在使用。所以也有对应的支持。</p>\n<p>用来支持 Java 的插件有好几个，但是官方有做了一个 Java 插件全家桶，一键安装好所有 Java 支持的插件。</p>\n<p><code>插件名：Java Extension Pack</code></p>\n<p>Java Extension Pack (Java 插件全家桶) 是一组流行的插件，可以帮助在 Visual Studio Code 中编写、测试和调试 Java 应用程序。</p>\n<p>这个全家桶包含了以下插件：</p>\n<ul>\n<li>📦 Java 语言支持（Red Hat 提供）<ul>\n<li>代码导航</li>\n<li>自动完成</li>\n<li>重构</li>\n<li>代码片段</li>\n</ul>\n</li>\n<li>📦 Java 调试器</li>\n<li>📦 Java 测试运行器<ul>\n<li>项目脚手架</li>\n<li>自定义目标</li>\n</ul>\n</li>\n<li>📦 Java 依赖查看器<ul>\n<li>查看 Java 项目、引用库、资源文件、包、类和类成员</li>\n</ul>\n</li>\n<li>Visual Studio IntelliCode<ul>\n<li>开发辅助</li>\n<li>完整的代码填充</li>\n</ul>\n</li>\n</ul>\n<p><img src=\"https://img-blog.csdnimg.cn/20200418190753329.png?x-oss-process=image/watermark,type_ZmFuZ3poZW5naGVpdGk,shadow_10,text_aHR0cHM6Ly9ibG9nLmNzZG4ubmV0L1RyaURpYW1vbmQ2,size_16,color_FFFFFF,t_70\"></p>\n<p><img src=\"https://imgconvert.csdnimg.cn/aHR0cHM6Ly91c2VyLWdvbGQtY2RuLnhpdHUuaW8vMjAyMC80LzEyLzE3MTZkMWNjMDhjNTA1NDM?x-oss-process=image/format,png\"></p>\n<h2 id=\"其他语言支持\"><a href=\"#其他语言支持\" class=\"headerlink\" title=\"其他语言支持\"></a>其他语言支持</h2><p>使用 VSCode 开发其他语言也是完全可以的，只要在插件搜索栏输入我们想用的语言，就可以找到那个语言的相关插件和支持。</p>\n<p><img src=\"https://img-blog.csdnimg.cn/20200418194052683.png?x-oss-process=image/watermark,type_ZmFuZ3poZW5naGVpdGk,shadow_10,text_aHR0cHM6Ly9ibG9nLmNzZG4ubmV0L1RyaURpYW1vbmQ2,size_16,color_FFFFFF,t_70\"></p>\n<p><img src=\"https://imgconvert.csdnimg.cn/aHR0cHM6Ly91c2VyLWdvbGQtY2RuLnhpdHUuaW8vMjAyMC80LzExLzE3MTY4NzdiNmRhMzMzNGM?x-oss-process=image/format,png\"></p>\n<h1 id=\"「待续」总结\"><a href=\"#「待续」总结\" class=\"headerlink\" title=\"「待续」总结\"></a>「待续」总结</h1><p><img src=\"https://img-blog.csdnimg.cn/20200423112626806.png?x-oss-process=image/watermark,type_ZmFuZ3poZW5naGVpdGk,shadow_10,text_aHR0cHM6Ly9ibG9nLmNzZG4ubmV0L1RyaURpYW1vbmQ2,size_16,color_FFFFFF,t_70\"></p>\n<p>对于一个个性化的编辑器，一箱好用的插件是必备的，没有插件的 VSCode 就等于没有了灵魂。这文章介绍了一大箱不同分类的超级实用、好用和常用的插件。</p>\n<p>但是这么多插件，一个一个安装，是不是想想都想放弃？还有一部分童鞋会说“IDE 的插件基本上都是安装好的，这个太麻烦了”。说实话确实很麻烦，特别是公司一台电脑，家里又一台手提电脑，两台电脑都需要安装这些插件，想想都崩溃了。</p>\n<p>当然每一个问题都有解决办法，VSCode 也有插件专门解决这种问题。VSCode 的<code>Setting Syn</code>可以帮助我们同步自己的插件，编辑器配置和自定义快捷键。让我们在新的环境或者电脑上，马上拉取以往的所有配置，再也不需要一个一个重新配置。</p>\n<p>下一篇文章我会详细讲说怎么配置和怎么使用<code>配置同步</code>插件。敬请期待哦！</p>\n","text":"上一篇文章《VSCode 常用快捷键大全》，我们了解到了 VSCode 中的常用快捷键。学会了快捷键可以让我们更高效和迅速的编写代码。但是没有 IDE 中的一些...","link":"","photos":[],"count_time":{"symbolsCount":"9.8k","symbolsTime":"9 mins."},"categories":[{"name":"Tools","slug":"Tools","count":3,"path":"api/categories/Tools.json"}],"tags":[{"name":"VSCode","slug":"VSCode","count":3,"path":"api/tags/VSCode.json"},{"name":"VSCode Plugins","slug":"VSCode-Plugins","count":1,"path":"api/tags/VSCode-Plugins.json"}],"toc":"<ol class=\"toc\"><li class=\"toc-item toc-level-1\"><a class=\"toc-link\" href=\"#%E3%80%8C%E4%B8%80%E3%80%8D%E5%9B%BD%E4%BA%BA%E5%BF%85%E5%A4%87%E9%9B%86%E5%90%88\"><span class=\"toc-text\">「一」国人必备集合</span></a><ol class=\"toc-child\"><li class=\"toc-item toc-level-2\"><a class=\"toc-link\" href=\"#VSCode-%E4%B8%AD%E6%96%87%E7%AE%80%E4%BD%93%E5%8C%85\"><span class=\"toc-text\">VSCode 中文简体包</span></a></li><li class=\"toc-item toc-level-2\"><a class=\"toc-link\" href=\"#%E4%BB%A3%E7%A0%81%E7%BF%BB%E8%AF%91\"><span class=\"toc-text\">代码翻译</span></a></li><li class=\"toc-item toc-level-2\"><a class=\"toc-link\" href=\"#%E6%A3%80%E6%B5%8B%E4%BB%A3%E7%A0%81%E8%8B%B1%E6%96%87%E5%8D%95%E8%AF%8D%E9%94%99%E8%AF%AF\"><span class=\"toc-text\">检测代码英文单词错误</span></a></li></ol></li><li class=\"toc-item toc-level-1\"><a class=\"toc-link\" href=\"#%E3%80%8C%E4%BA%8C%E3%80%8D%E4%B8%BB%E9%A2%98%E9%9B%86%E5%90%88\"><span class=\"toc-text\">「二」主题集合</span></a><ol class=\"toc-child\"><li class=\"toc-item toc-level-2\"><a class=\"toc-link\" href=\"#Dracula-Theme\"><span class=\"toc-text\">Dracula Theme</span></a></li><li class=\"toc-item toc-level-2\"><a class=\"toc-link\" href=\"#Material-Theme\"><span class=\"toc-text\">Material Theme</span></a></li><li class=\"toc-item toc-level-2\"><a class=\"toc-link\" href=\"#Nebula-Theme\"><span class=\"toc-text\">Nebula Theme</span></a></li><li class=\"toc-item toc-level-2\"><a class=\"toc-link\" href=\"#Atom-One-Dark-Theme\"><span class=\"toc-text\">Atom One Dark Theme</span></a></li><li class=\"toc-item toc-level-2\"><a class=\"toc-link\" href=\"#One-Monokai-Theme\"><span class=\"toc-text\">One Monokai Theme</span></a></li><li class=\"toc-item toc-level-2\"><a class=\"toc-link\" href=\"#GitHub-Plus-Theme\"><span class=\"toc-text\">GitHub Plus Theme</span></a></li></ol></li><li class=\"toc-item toc-level-1\"><a class=\"toc-link\" href=\"#%E3%80%8C%E4%B8%89%E3%80%8D%E5%9B%BE%E6%A0%87%E4%B8%BB%E9%A2%98%E9%9B%86%E5%90%88\"><span class=\"toc-text\">「三」图标主题集合</span></a><ol class=\"toc-child\"><li class=\"toc-item toc-level-2\"><a class=\"toc-link\" href=\"#Material-Icon-Theme\"><span class=\"toc-text\">Material Icon Theme</span></a></li><li class=\"toc-item toc-level-2\"><a class=\"toc-link\" href=\"#VSCode-Icons\"><span class=\"toc-text\">VSCode Icons</span></a></li></ol></li><li class=\"toc-item toc-level-1\"><a class=\"toc-link\" href=\"#%E3%80%8C%E5%9B%9B%E3%80%8D%E5%AE%9E%E7%94%A8%E6%8F%92%E4%BB%B6%E9%9B%86%E5%90%88\"><span class=\"toc-text\">「四」实用插件集合</span></a><ol class=\"toc-child\"><li class=\"toc-item toc-level-2\"><a class=\"toc-link\" href=\"#%E4%BB%A3%E7%A0%81%E4%B9%A6%E7%AD%BE\"><span class=\"toc-text\">代码书签</span></a></li><li class=\"toc-item toc-level-2\"><a class=\"toc-link\" href=\"#%E6%8B%AC%E5%8F%B7%E5%AF%B9%E5%BD%A9%E8%89%B2%E5%8C%96\"><span class=\"toc-text\">括号对彩色化</span></a></li><li class=\"toc-item toc-level-2\"><a class=\"toc-link\" href=\"#%E5%A2%9E%E5%BC%BA-Git-%E5%8A%9F%E8%83%BD\"><span class=\"toc-text\">增强 Git 功能</span></a></li><li class=\"toc-item toc-level-2\"><a class=\"toc-link\" href=\"#Git-%E5%8E%86%E5%8F%B2%E8%AE%B0%E5%BD%95\"><span class=\"toc-text\">Git 历史记录</span></a></li><li class=\"toc-item toc-level-2\"><a class=\"toc-link\" href=\"#%E5%AE%9E%E6%97%B6%E5%8D%8F%E4%BD%9C%E7%BC%96%E8%BE%91\"><span class=\"toc-text\">实时协作编辑</span></a></li><li class=\"toc-item toc-level-2\"><a class=\"toc-link\" href=\"#%E8%B7%AF%E5%BE%84%E6%99%BA%E8%83%BD%E6%8F%90%E7%A4%BA\"><span class=\"toc-text\">路径智能提示</span></a></li></ol></li><li class=\"toc-item toc-level-1\"><a class=\"toc-link\" href=\"#%E3%80%8C%E4%BA%94%E3%80%8D%E5%89%8D%E7%AB%AF%E5%BC%80%E5%8F%91%E6%8F%92%E4%BB%B6%E9%9B%86%E5%90%88\"><span class=\"toc-text\">「五」前端开发插件集合</span></a><ol class=\"toc-child\"><li class=\"toc-item toc-level-2\"><a class=\"toc-link\" href=\"#%E8%87%AA%E5%8A%A8%E5%85%B3%E9%97%AD%E6%A0%87%E7%AD%BE\"><span class=\"toc-text\">自动关闭标签</span></a></li><li class=\"toc-item toc-level-2\"><a class=\"toc-link\" href=\"#%E8%87%AA%E5%8A%A8%E5%90%8C%E6%AD%A5%E6%A0%87%E7%AD%BE%E5%90%8D\"><span class=\"toc-text\">自动同步标签名</span></a></li><li class=\"toc-item toc-level-2\"><a class=\"toc-link\" href=\"#CSS-%E9%A2%9C%E8%89%B2%E9%AB%98%E4%BA%AE\"><span class=\"toc-text\">CSS 颜色高亮</span></a></li><li class=\"toc-item toc-level-2\"><a class=\"toc-link\" href=\"#%E9%AB%98%E4%BA%AE%E5%8C%B9%E5%AF%B9%E6%A0%87%E7%AD%BE\"><span class=\"toc-text\">高亮匹对标签</span></a></li><li class=\"toc-item toc-level-2\"><a class=\"toc-link\" href=\"#HTML-CSS-%E6%94%AF%E6%8C%81\"><span class=\"toc-text\">HTML CSS 支持</span></a></li><li class=\"toc-item toc-level-2\"><a class=\"toc-link\" href=\"#%E5%B0%8F%E7%A8%8B%E5%BA%8F%E6%94%AF%E6%8C%81\"><span class=\"toc-text\">小程序支持</span></a></li><li class=\"toc-item toc-level-2\"><a class=\"toc-link\" href=\"#Vue-%E6%94%AF%E6%8C%81\"><span class=\"toc-text\">Vue 支持</span></a></li><li class=\"toc-item toc-level-2\"><a class=\"toc-link\" href=\"#React-%E6%94%AF%E6%8C%81\"><span class=\"toc-text\">React 支持</span></a></li><li class=\"toc-item toc-level-2\"><a class=\"toc-link\" href=\"#NPM-%E6%94%AF%E6%8C%81\"><span class=\"toc-text\">NPM 支持</span></a></li><li class=\"toc-item toc-level-2\"><a class=\"toc-link\" href=\"#NPM-%E6%99%BA%E8%83%BD%E6%8F%90%E7%A4%BA\"><span class=\"toc-text\">NPM 智能提示</span></a></li><li class=\"toc-item toc-level-2\"><a class=\"toc-link\" href=\"#%E5%BC%BA%E5%A4%A7%E7%9A%84%E4%BB%A3%E7%A0%81%E6%A0%BC%E5%BC%8F%E5%8C%96\"><span class=\"toc-text\">强大的代码格式化</span></a></li><li class=\"toc-item toc-level-2\"><a class=\"toc-link\" href=\"#%E7%BC%96%E8%BE%91%E5%99%A8%E4%B8%AD%E7%9A%84%E5%AE%9E%E6%97%B6%E9%A2%84%E8%A7%88\"><span class=\"toc-text\">编辑器中的实时预览</span></a></li><li class=\"toc-item toc-level-2\"><a class=\"toc-link\" href=\"#%E5%AE%9E%E6%97%B6%E9%A2%84%E8%A7%88\"><span class=\"toc-text\">实时预览</span></a></li><li class=\"toc-item toc-level-2\"><a class=\"toc-link\" href=\"#%E6%B5%8F%E8%A7%88%E5%99%A8%E6%89%93%E5%BC%80\"><span class=\"toc-text\">浏览器打开</span></a></li></ol></li><li class=\"toc-item toc-level-1\"><a class=\"toc-link\" href=\"#%E3%80%8C%E5%85%AD%E3%80%8DPHP-%E5%BC%80%E5%8F%91%E6%8F%92%E4%BB%B6\"><span class=\"toc-text\">「六」PHP 开发插件</span></a><ol class=\"toc-child\"><li class=\"toc-item toc-level-2\"><a class=\"toc-link\" href=\"#PHP-%E5%BC%BA%E5%8C%96%E6%8F%92%E4%BB%B6\"><span class=\"toc-text\">PHP 强化插件</span></a></li><li class=\"toc-item toc-level-2\"><a class=\"toc-link\" href=\"#PHP-%E8%A7%84%E8%8C%83%E6%A3%80%E6%B5%8B\"><span class=\"toc-text\">PHP 规范检测</span></a></li></ol></li><li class=\"toc-item toc-level-1\"><a class=\"toc-link\" href=\"#%E3%80%8C%E4%B8%83%E3%80%8DJava-%E5%BC%80%E5%8F%91%E6%8F%92%E4%BB%B6\"><span class=\"toc-text\">「七」Java 开发插件</span></a><ol class=\"toc-child\"><li class=\"toc-item toc-level-2\"><a class=\"toc-link\" href=\"#%E5%85%B6%E4%BB%96%E8%AF%AD%E8%A8%80%E6%94%AF%E6%8C%81\"><span class=\"toc-text\">其他语言支持</span></a></li></ol></li><li class=\"toc-item toc-level-1\"><a class=\"toc-link\" href=\"#%E3%80%8C%E5%BE%85%E7%BB%AD%E3%80%8D%E6%80%BB%E7%BB%93\"><span class=\"toc-text\">「待续」总结</span></a></li></ol>","author":{"name":"三钻","slug":"blog-author","avatar":"https://ik.imagekit.io/bennyxguo/ObsidianestLogo-hex_hecqbw.png?updatedAt=1692679397324","link":"/","description":"<p>Programming a piece of art.</p> <p>用<b>匠人精神</b>开发出<b>艺术</b>。</p>","socials":{"github":"https://github.com/TriDiamond","twitter":"","stackoverflow":"","wechat":"","qq":"","weibo":"https://weibo.com/u/7318914058","zhihu":"https://www.zhihu.com/people/tridiamond","csdn":"https://blog.csdn.net/TriDiamond6","juejin":"https://juejin.cn/user/1873223546578589","customs":{"bilibili":{"icon":"https://tridiamond.tech/svg/bilibili.svg","link":"https://live.bilibili.com/22619211"}}}},"mapped":true,"hidden":false,"prev_post":{"title":"VSCode配置同步","uid":"8b2cfe872b7cb9696e1812ee34aa03bc","slug":"8b2cfe872b7cb9696e1812ee34aa03bc","date":"2020-05-01T02:11:07.000Z","updated":"2023-08-22T04:44:05.511Z","comments":true,"path":"api/articles/8b2cfe872b7cb9696e1812ee34aa03bc.json","keywords":null,"cover":"https://source.unsplash.com/PUvPZckRnOg/1200x628","text":"在上两篇文章中，我们学到了 VSCode 是怎么使用快捷键让我们编写代码时更灵活便捷，甚至是可以基本脱离鼠标。还介绍了很多常用的插件让我们如虎添翼，就像 VSC...","link":"","photos":[],"count_time":{"symbolsCount":"7.6k","symbolsTime":"7 mins."},"categories":[{"name":"Tools","slug":"Tools","count":3,"path":"api/categories/Tools.json"}],"tags":[{"name":"VSCode","slug":"VSCode","count":3,"path":"api/tags/VSCode.json"},{"name":"VSCode Settings","slug":"VSCode-Settings","count":1,"path":"api/tags/VSCode-Settings.json"}],"author":{"name":"三钻","slug":"blog-author","avatar":"https://ik.imagekit.io/bennyxguo/ObsidianestLogo-hex_hecqbw.png?updatedAt=1692679397324","link":"/","description":"<p>Programming a piece of art.</p> <p>用<b>匠人精神</b>开发出<b>艺术</b>。</p>","socials":{"github":"https://github.com/TriDiamond","twitter":"","stackoverflow":"","wechat":"","qq":"","weibo":"https://weibo.com/u/7318914058","zhihu":"https://www.zhihu.com/people/tridiamond","csdn":"https://blog.csdn.net/TriDiamond6","juejin":"https://juejin.cn/user/1873223546578589","customs":{"bilibili":{"icon":"https://tridiamond.tech/svg/bilibili.svg","link":"https://live.bilibili.com/22619211"}}}}},"next_post":{"title":"VSCode常用快捷键大全","uid":"dc4e2e8dd5224ff3b1a1b269ea5930dc","slug":"dc4e2e8dd5224ff3b1a1b269ea5930dc","date":"2020-04-19T12:18:46.000Z","updated":"2023-08-22T04:44:05.511Z","comments":true,"path":"api/articles/dc4e2e8dd5224ff3b1a1b269ea5930dc.json","keywords":null,"cover":"https://source.unsplash.com/LqztBrFUkec/1200x628","text":"我之前也是用过很多代码编辑器，从NotePad++、SublimeText一直到PHPStorm，最后VSCode。这个过程每一个编辑器我都折腾了很多配置，插件...","link":"","photos":[],"count_time":{"symbolsCount":"6.7k","symbolsTime":"6 mins."},"categories":[{"name":"Tools","slug":"Tools","count":3,"path":"api/categories/Tools.json"}],"tags":[{"name":"VSCode","slug":"VSCode","count":3,"path":"api/tags/VSCode.json"},{"name":"VSCode Shortcuts","slug":"VSCode-Shortcuts","count":1,"path":"api/tags/VSCode-Shortcuts.json"}],"author":{"name":"三钻","slug":"blog-author","avatar":"https://ik.imagekit.io/bennyxguo/ObsidianestLogo-hex_hecqbw.png?updatedAt=1692679397324","link":"/","description":"<p>Programming a piece of art.</p> <p>用<b>匠人精神</b>开发出<b>艺术</b>。</p>","socials":{"github":"https://github.com/TriDiamond","twitter":"","stackoverflow":"","wechat":"","qq":"","weibo":"https://weibo.com/u/7318914058","zhihu":"https://www.zhihu.com/people/tridiamond","csdn":"https://blog.csdn.net/TriDiamond6","juejin":"https://juejin.cn/user/1873223546578589","customs":{"bilibili":{"icon":"https://tridiamond.tech/svg/bilibili.svg","link":"https://live.bilibili.com/22619211"}}}}}}