[{"name":"Linked List","path":"api/tags/Linked-List.json","slug":"Linked-List","count":1},{"name":"Array","path":"api/tags/Array.json","slug":"Array","count":1},{"name":"Jump List","path":"api/tags/Jump-List.json","slug":"Jump-List","count":1},{"name":"Algorithm","path":"api/tags/Algorithm.json","slug":"Algorithm","count":2},{"name":"Data Structure","path":"api/tags/Data-Structure.json","slug":"Data-Structure","count":1},{"name":"Time Complexity","path":"api/tags/Time-Complexity.json","slug":"Time-Complexity","count":1},{"name":"Space Complexity","path":"api/tags/Space-Complexity.json","slug":"Space-Complexity","count":1},{"name":"LeetCode","path":"api/tags/LeetCode.json","slug":"LeetCode","count":1},{"name":"aurora","path":"api/tags/aurora.json","slug":"aurora","count":1},{"name":"project-blog","path":"api/tags/project-blog.json","slug":"project-blog","count":1},{"name":"PHP","path":"api/tags/PHP.json","slug":"PHP","count":1},{"name":"Service","path":"api/tags/Service.json","slug":"Service","count":1},{"name":"Architecture","path":"api/tags/Architecture.json","slug":"Architecture","count":1},{"name":"HTML&CSS","path":"api/tags/HTML-CSS.json","slug":"HTML-CSS","count":4},{"name":"CSS Animation","path":"api/tags/CSS-Animation.json","slug":"CSS-Animation","count":1},{"name":"JavaScript","path":"api/tags/JavaScript.json","slug":"JavaScript","count":4},{"name":"Browser","path":"api/tags/Browser.json","slug":"Browser","count":2},{"name":"Console","path":"api/tags/Console.json","slug":"Console","count":1},{"name":"Debugging","path":"api/tags/Debugging.json","slug":"Debugging","count":1},{"name":"Vue","path":"api/tags/Vue.json","slug":"Vue","count":1},{"name":"Vue3","path":"api/tags/Vue3.json","slug":"Vue3","count":1},{"name":"Free Code Camp","path":"api/tags/Free-Code-Camp.json","slug":"Free-Code-Camp","count":3},{"name":"FrontEnd","path":"api/tags/FrontEnd.json","slug":"FrontEnd","count":1},{"name":"ES6","path":"api/tags/ES6.json","slug":"ES6","count":1},{"name":"Interview","path":"api/tags/Interview.json","slug":"Interview","count":1},{"name":"Ionic 2","path":"api/tags/Ionic-2.json","slug":"Ionic-2","count":3},{"name":"Angular 2","path":"api/tags/Angular-2.json","slug":"Angular-2","count":2},{"name":"Hybird App","path":"api/tags/Hybird-App.json","slug":"Hybird-App","count":6},{"name":"Ionic 3","path":"api/tags/Ionic-3.json","slug":"Ionic-3","count":3},{"name":"Angular 4","path":"api/tags/Angular-4.json","slug":"Angular-4","count":4},{"name":"Laravel 5.4","path":"api/tags/Laravel-5-4.json","slug":"Laravel-5-4","count":1},{"name":"Laravel Passport","path":"api/tags/Laravel-Passport.json","slug":"Laravel-Passport","count":3},{"name":"Lumen","path":"api/tags/Lumen.json","slug":"Lumen","count":2},{"name":"Programmer","path":"api/tags/Programmer.json","slug":"Programmer","count":3},{"name":"Better Programming","path":"api/tags/Better-Programming.json","slug":"Better-Programming","count":3},{"name":"Learning","path":"api/tags/Learning.json","slug":"Learning","count":1},{"name":"Programming","path":"api/tags/Programming.json","slug":"Programming","count":1},{"name":"Notes","path":"api/tags/Notes.json","slug":"Notes","count":1},{"name":"Gitlab","path":"api/tags/Gitlab.json","slug":"Gitlab","count":1},{"name":"Webhook","path":"api/tags/Webhook.json","slug":"Webhook","count":1},{"name":"VSCode","path":"api/tags/VSCode.json","slug":"VSCode","count":3},{"name":"VSCode Plugins","path":"api/tags/VSCode-Plugins.json","slug":"VSCode-Plugins","count":1},{"name":"VSCode Settings","path":"api/tags/VSCode-Settings.json","slug":"VSCode-Settings","count":1},{"name":"VSCode Shortcuts","path":"api/tags/VSCode-Shortcuts.json","slug":"VSCode-Shortcuts","count":1}]